mycalc/calculator.py
jieunim2243255-0.0.1.dist-info/METADATA
jieunim2243255-0.0.1.dist-info/WHEEL
jieunim2243255-0.0.1.dist-info/top_level.txt
jieunim2243255-0.0.1.dist-info/RECORD
