Metadata-Version: 2.1
Name: jieunim2243255
Version: 0.0.1
Summary: nice calc
Home-page: https://github.com/Jieun-IM/calc0001
Download-URL: https://github.com/Jieun-IM/calc0001/releases/tag/v0.0.1
Author: jieunim
License: UNKNOWN
Platform: UNKNOWN
Classifier: Programming Language :: Python :: 3
